pyPhases/Data.py
pyPhases/Phase.py
pyPhases/Project.py
pyPhases/Stage.py
pyPhases/__init__.py
pyPhases/__main__.py
pyPhases/decorator/Decorator.py
pyPhases/decorator/ExportValidator.py
pyPhases/decorator/__init__.py
pyPhases/exporter/DataExporter.py
pyPhases/exporter/KerasExporter.py
pyPhases/exporter/ObjectExporter.py
pyPhases/exporter/__init__.py
pyPhases/publisher/DotScience.py
pyPhases/publisher/Publisher.py
pyPhases/publisher/__init__.py
pyPhases/storage/ArrayStorage.py
pyPhases/storage/FileStorage.py
pyPhases/storage/Storage.py
pyPhases/storage/__init__.py
pyPhases/util/FileWrapper.py
pyPhases/util/Logger.py
pyPhases/util/Optionizable.py
pyPhases/util/__init__.py
tests/__init__.py
tests/test_acceptance.py
tests/test_arraystorage.py
tests/test_exporter copy.py
tests/test_kerasexporter.py
tests/test_objectexporter.py
pyPhases-0.2.4.dist-info/LICENSE
pyPhases-0.2.4.dist-info/METADATA
pyPhases-0.2.4.dist-info/WHEEL
pyPhases-0.2.4.dist-info/top_level.txt
pyPhases-0.2.4.dist-info/RECORD
