Metadata-Version: 2.1
Name: pyPhases
Version: 0.2.4
Summary: A Framework for creating a boilerplate template for ai projects that are ready for MLOps
Home-page: https://gitlab.com/tud.ibmt/pyPhases
Author: Franz Ehrlich
Author-email: fehrlichd@gmail.com
License: UNKNOWN
Platform: UNKNOWN
Classifier: Programming Language :: Python :: 3
Classifier: License :: OSI Approved :: MIT License
Classifier: Operating System :: OS Independent
Requires-Python: >=3.5
Requires-Dist: pyarrow
Requires-Dist: numpy
